chaine/logging.py
chaine/crf.py
chaine/__init__.py
chaine/typing.py
chaine/training.py
chaine/validation.py
chaine/_core/crf.cpp
chaine/_core/trainer_wrapper.hpp
chaine/_core/crf.cpython-313-darwin.so
chaine/_core/tagger_wrapper.hpp
chaine/_core/crf.pyx
chaine/_core/crfsuite_api.pxd
chaine/_core/trainer_wrapper.cpp
chaine/_core/liblbfgs/README
chaine/_core/liblbfgs/COPYING
chaine/_core/liblbfgs/include/lbfgs.h
chaine/_core/liblbfgs/lib/arithmetic_sse_float.h
chaine/_core/liblbfgs/lib/arithmetic_ansi.h
chaine/_core/liblbfgs/lib/arithmetic_sse_double.h
chaine/_core/liblbfgs/lib/lbfgs.c
chaine/_core/crfsuite/README
chaine/_core/crfsuite/COPYING
chaine/_core/crfsuite/swig/crfsuite.cpp
chaine/_core/crfsuite/include/crfsuite_api.hpp
chaine/_core/crfsuite/include/os.h
chaine/_core/crfsuite/include/crfsuite.h
chaine/_core/crfsuite/include/crfsuite.hpp
chaine/_core/crfsuite/lib/crf/src/crf1d_context.c
chaine/_core/crfsuite/lib/crf/src/dictionary.c
chaine/_core/crfsuite/lib/crf/src/json.c
chaine/_core/crfsuite/lib/crf/src/train_arow.c
chaine/_core/crfsuite/lib/crf/src/train_averaged_perceptron.c
chaine/_core/crfsuite/lib/crf/src/dataset.c
chaine/_core/crfsuite/lib/crf/src/crf1d_feature.c
chaine/_core/crfsuite/lib/crf/src/quark.h
chaine/_core/crfsuite/lib/crf/src/params.h
chaine/_core/crfsuite/lib/crf/src/crf1d_tag.c
chaine/_core/crfsuite/lib/crf/src/vecmath.h
chaine/_core/crfsuite/lib/crf/src/crfsuite_internal.h
chaine/_core/crfsuite/lib/crf/src/train_l2sgd.c
chaine/_core/crfsuite/lib/crf/src/holdout.c
chaine/_core/crfsuite/lib/crf/src/logging.h
chaine/_core/crfsuite/lib/crf/src/crfsuite_train.c
chaine/_core/crfsuite/lib/crf/src/rumavl.h
chaine/_core/crfsuite/lib/crf/src/crf1d_encode.c
chaine/_core/crfsuite/lib/crf/src/json.h
chaine/_core/crfsuite/lib/crf/src/crf1d.h
chaine/_core/crfsuite/lib/crf/src/train_passive_aggressive.c
chaine/_core/crfsuite/lib/crf/src/quark.c
chaine/_core/crfsuite/lib/crf/src/params.c
chaine-3.13.1.dist-info/RECORD
chaine-3.13.1.dist-info/WHEEL
chaine-3.13.1.dist-info/METADATA
