Metadata-Version: 2.1
Name: chaine
Version: 3.13.1
Summary: Linear-chain conditional random fields for natural language processing
Author: Severin Simmler
Author-email: s.simmler@snapaddy.com
Requires-Python: >=3.10,<4.0
Classifier: Programming Language :: Python :: 3
Classifier: Programming Language :: Python :: 3.10
Classifier: Programming Language :: Python :: 3.11
Classifier: Programming Language :: Python :: 3.12
Classifier: Programming Language :: Python :: 3.13
